pymoogo/__init__.py
pymoogo/client.py
pymoogo/exceptions.py
pymoogo/models.py
pymoogo-1.0.1.dist-info/licenses/LICENSE
pymoogo-1.0.1.dist-info/METADATA
pymoogo-1.0.1.dist-info/WHEEL
pymoogo-1.0.1.dist-info/top_level.txt
pymoogo-1.0.1.dist-info/RECORD
