Metadata-Version: 2.4
Name: pymoogo
Version: 1.0.1
Summary: Python client library for Moogo smart spray system API
Author-email: Bryan Li <bryan.li@gmail.com>
License-Expression: MIT
Project-URL: Homepage, https://github.com/joyfulhouse/pymoogo
Project-URL: Documentation, https://github.com/joyfulhouse/pymoogo
Project-URL: Repository, https://github.com/joyfulhouse/pymoogo
Project-URL: Issues, https://github.com/joyfulhouse/pymoogo/issues
Classifier: Development Status :: 4 - Beta
Classifier: Intended Audience :: Developers
Classifier: Operating System :: OS Independent
Classifier: Programming Language :: Python :: 3
Classifier: Programming Language :: Python :: 3.13
Classifier: Programming Language :: Python :: 3.14
Requires-Python: >=3.13
License-File: LICENSE
Requires-Dist: aiohttp>=3.13.0
Provides-Extra: dev
Requires-Dist: pytest>=9.0.0; extra == "dev"
Requires-Dist: pytest-asyncio>=1.3.0; extra == "dev"
Requires-Dist: pytest-cov>=7.0.0; extra == "dev"
Requires-Dist: mypy>=1.18.0; extra == "dev"
Requires-Dist: ruff>=0.14.5; extra == "dev"
Requires-Dist: python-dotenv>=1.2.0; extra == "dev"
Dynamic: license-file
